yyxx_game_pkg_dev/__init__.py
yyxx_game_pkg_dev/pandas_test/__init__.py
yyxx_game_pkg_dev/pandas_test/helper.py
yyxx_game_pkg_dev/temp/__init__.py
yyxx_game_pkg_dev/temp/hello.py
yyxx_game_pkg_dev/xtrace/__init__.py
yyxx_game_pkg_dev/xtrace/helper.py
yyxx_game_pkg_dev-2023.3.7.1.dist-info/METADATA
yyxx_game_pkg_dev-2023.3.7.1.dist-info/WHEEL
yyxx_game_pkg_dev-2023.3.7.1.dist-info/RECORD
