Metadata-Version: 2.1
Name: yyxx-game-pkg-dev
Version: 2023.3.7.1
Summary: yyxx game custom module
Home-page: https://github.com/yuanyou-tech/git-pypi-dev.git
License: MIT
Author: yyxxx-game
Requires-Python: >=3.8
Classifier: License :: OSI Approved :: MIT License
Classifier: Operating System :: OS Independent
Classifier: Programming Language :: Python :: 3
Classifier: Programming Language :: Python :: 3.8
Classifier: Programming Language :: Python :: 3.9
Classifier: Programming Language :: Python :: 3.10
Classifier: Programming Language :: Python :: 3.11
Classifier: Programming Language :: Python :: 3
Requires-Dist: opentelemetry-api (>=1.16.0,<2.0.0)
Requires-Dist: opentelemetry-exporter-jaeger (>=1.16.0,<2.0.0)
Requires-Dist: opentelemetry-instrumentation-requests (>=0.37b0,<0.38)
Requires-Dist: opentelemetry-sdk (>=1.16.0,<2.0.0)
Requires-Dist: pandas (>=1.5.3,<2.0.0)
Requires-Dist: toml (>=0.10.2,<0.11.0)
Project-URL: Repository, https://github.com/yuanyou-tech/git-pypi-dev.git
